trading212api/__init__.py
trading212api-0.1.1.dist-info/METADATA
trading212api-0.1.1.dist-info/WHEEL
trading212api-0.1.1.dist-info/top_level.txt
trading212api-0.1.1.dist-info/RECORD
