Metadata-Version: 2.1
Name: trading212api
Version: 0.1.1
Summary: An unofficial API library for Trading212 based on Selenium
Home-page: https://github.com/auino/trading212api
Author: Enrico Cambiaso
Author-email: enrico.cambiaso@gmail.com
License: UNKNOWN
Platform: UNKNOWN
Classifier: Programming Language :: Python :: 3
Classifier: License :: OSI Approved :: MIT License
Classifier: Operating System :: OS Independent
Requires-Python: >=3.6
